{
  "es": {
    "announcements": "Anuncios",
    "publish_announcements": "Publicar Anuncios",
    "create_announcement": "Crear Anuncio",
    "edit_announcement": "Editar Anuncio",
    "delete_announcement": "Eliminar Anuncio",
    "view_announcement": "Ver Anuncio",
    "announcement_title": "Título del Anuncio",
    "announcement_description": "Descripción",
    "announcement_price": "Precio",
    "announcement_category": "Categoría",
    "announcement_image": "Imagen",
    "announcement_video": "Video",
    "announcement_featured": "Destacado",
    "announcement_active": "Activo",
    "buy_now": "Comprar Ahora",
    "add_to_cart": "Añadir al Carrito",
    "announcement_details": "Detalles del Anuncio",
    "announcement_created": "Anuncio creado exitosamente",
    "announcement_updated": "Anuncio actualizado exitosamente",
    "announcement_deleted": "Anuncio eliminado exitosamente",
    "confirm_delete_announcement": "¿Estás seguro de que quieres eliminar este anuncio?",
    "no_announcements": "No hay anuncios disponibles",
    "loading_announcements": "Cargando anuncios...",
    "announcement_form_title": "Formulario de Anuncio",
    "announcement_form_name": "Nombre del Producto",
    "announcement_form_description": "Descripción del Producto",
    "announcement_form_price": "Precio (€)",
    "announcement_form_image_url": "URL de Imagen",
    "announcement_form_video_url": "URL de Video",
    "announcement_form_youtube_url": "URL de YouTube",
    "announcement_form_category": "Categoría",
    "announcement_form_featured": "Marcar como Destacado",
    "announcement_form_active": "Marcar como Activo",
    "announcement_form_save": "Guardar Anuncio",
    "announcement_form_cancel": "Cancelar",
    "announcement_form_reset": "Limpiar Formulario",
    "announcement_form_preview": "Vista Previa",
    "announcement_form_test_html": "Probar HTML",
    "announcement_validation_name_required": "El nombre es requerido",
    "announcement_validation_description_required": "La descripción es requerida",
    "announcement_validation_price_required": "El precio es requerido",
    "announcement_validation_price_invalid": "El precio debe ser un número válido",
    "announcement_management": "Gestión de Anuncios",
    "announcement_list": "Lista de Anuncios",
    "announcement_actions": "Acciones",
    "announcement_created_at": "Fecha de Creación",
    "announcement_updated_at": "Última Actualización"
  },
  "en": {
    "announcements": "Announcements",
    "publish_announcements": "Publish Announcements",
    "create_announcement": "Create Announcement",
    "edit_announcement": "Edit Announcement",
    "delete_announcement": "Delete Announcement",
    "view_announcement": "View Announcement",
    "announcement_title": "Announcement Title",
    "announcement_description": "Description",
    "announcement_price": "Price",
    "announcement_category": "Category",
    "announcement_image": "Image",
    "announcement_video": "Video",
    "announcement_featured": "Featured",
    "announcement_active": "Active",
    "buy_now": "Buy Now",
    "add_to_cart": "Add to Cart",
    "announcement_details": "Announcement Details",
    "announcement_created": "Announcement created successfully",
    "announcement_updated": "Announcement updated successfully",
    "announcement_deleted": "Announcement deleted successfully",
    "confirm_delete_announcement": "Are you sure you want to delete this announcement?",
    "no_announcements": "No announcements available",
    "loading_announcements": "Loading announcements...",
    "announcement_form_title": "Announcement Form",
    "announcement_form_name": "Product Name",
    "announcement_form_description": "Product Description",
    "announcement_form_price": "Price (€)",
    "announcement_form_image_url": "Image URL",
    "announcement_form_video_url": "Video URL",
    "announcement_form_youtube_url": "YouTube URL",
    "announcement_form_category": "Category",
    "announcement_form_featured": "Mark as Featured",
    "announcement_form_active": "Mark as Active",
    "announcement_form_save": "Save Announcement",
    "announcement_form_cancel": "Cancel",
    "announcement_form_reset": "Clear Form",
    "announcement_form_preview": "Preview",
    "announcement_form_test_html": "Test HTML",
    "announcement_validation_name_required": "Name is required",
    "announcement_validation_description_required": "Description is required",
    "announcement_validation_price_required": "Price is required",
    "announcement_validation_price_invalid": "Price must be a valid number",
    "announcement_management": "Announcement Management",
    "announcement_list": "Announcement List",
    "announcement_actions": "Actions",
    "announcement_created_at": "Created At",
    "announcement_updated_at": "Last Updated"
  }
}
